igm/__init__.py
igm/common.py
igm/igm_run.py
igm/instructed_oggm.py
igm/emulators/f15_cfsflow_GJ_22_a/README.md
igm/emulators/f15_cfsflow_GJ_22_a/100/fieldin.dat
igm/emulators/f15_cfsflow_GJ_22_a/100/fieldout.dat
igm/emulators/f15_cfsflow_GJ_22_a/100/model.h5
igm/emulators/f15_cfsflow_GJ_22_a/200/fieldin.dat
igm/emulators/f15_cfsflow_GJ_22_a/200/fieldout.dat
igm/emulators/f15_cfsflow_GJ_22_a/200/model.h5
igm/emulators/f15_cfsflow_GJ_22_a/50/fieldin.dat
igm/emulators/f15_cfsflow_GJ_22_a/50/fieldout.dat
igm/emulators/f15_cfsflow_GJ_22_a/50/model.h5
igm/emulators/pinnbp_10_4_cnn_16_16_3_1/fieldin.dat
igm/emulators/pinnbp_10_4_cnn_16_16_3_1/fieldout.dat
igm/emulators/pinnbp_10_4_cnn_16_16_3_1/model.h5
igm/emulators/pinnbp_10_4_cnn_16_32_2_0/fieldin.dat
igm/emulators/pinnbp_10_4_cnn_16_32_2_0/fieldout.dat
igm/emulators/pinnbp_10_4_cnn_16_32_2_0/model.h5
igm/emulators/pinnbp_10_4_cnn_16_32_2_1/fieldin.dat
igm/emulators/pinnbp_10_4_cnn_16_32_2_1/fieldout.dat
igm/emulators/pinnbp_10_4_cnn_16_32_2_1/model.h5
igm/emulators/pinnbp_10_4_cnn_16_32_3_0/fieldin.dat
igm/emulators/pinnbp_10_4_cnn_16_32_3_0/fieldout.dat
igm/emulators/pinnbp_10_4_cnn_16_32_3_0/model.h5
igm/emulators/pinnbp_10_4_cnn_16_32_3_1/fieldin.dat
igm/emulators/pinnbp_10_4_cnn_16_32_3_1/fieldout.dat
igm/emulators/pinnbp_10_4_cnn_16_32_3_1/model.h5
igm/emulators/pinnbp_10_4_cnn_8_32_2_0/fieldin.dat
igm/emulators/pinnbp_10_4_cnn_8_32_2_0/fieldout.dat
igm/emulators/pinnbp_10_4_cnn_8_32_2_0/model.h5
igm/emulators/pinnbp_10_4_cnn_8_32_2_1/fieldin.dat
igm/emulators/pinnbp_10_4_cnn_8_32_2_1/fieldout.dat
igm/emulators/pinnbp_10_4_cnn_8_32_2_1/model.h5
igm/emulators/pinnbp_30_4_cnn_12_32_3_1/fieldin.dat
igm/emulators/pinnbp_30_4_cnn_12_32_3_1/fieldout.dat
igm/emulators/pinnbp_30_4_cnn_12_32_3_1/model.h5
igm/modules/__init__.py
igm/modules/utils.py
igm/modules/postproc/__init__.py
igm/modules/postproc/anim_mayavi/__init__.py
igm/modules/postproc/anim_mayavi/anim_mayavi.py
igm/modules/postproc/anim_plotly/__init__.py
igm_model_dev-2.1.0.dist-info/LICENSE
igm_model_dev-2.1.0.dist-info/METADATA
igm_model_dev-2.1.0.dist-info/WHEEL
igm_model_dev-2.1.0.dist-info/entry_points.txt
igm_model_dev-2.1.0.dist-info/top_level.txt
igm_model_dev-2.1.0.dist-info/RECORD
