Metadata-Version: 2.1
Name: igm-model-dev
Version: 2.1.0
Summary: IGM - a glacier evolution model
Home-page: https://github.com/jouvetg/igm
Author: Guillaume Jouvet
Author-email: guillaume.jouvet@unil.ch
License: gpl-3.0
Requires-Python: <3.12
License-File: LICENSE
Requires-Dist: tensorflow[and-cuda]
Requires-Dist: matplotlib
Requires-Dist: scipy
Requires-Dist: netCDF4
Requires-Dist: xarray
Requires-Dist: rasterio
Requires-Dist: pyproj
Requires-Dist: geopandas
Requires-Dist: oggm
Requires-Dist: importlib-resources
